[
  {
    "Username": "cmorby0",
    "Email": "cimm0@jimdo.com",
    "Avatar": "https://robohash.org/sitvoluptatemrerum.png?size=250x250&set=set1",
    "City": "Ukhta",
    "DateOfBirth": "2019-01-18T10:30:31Z",
    "Gender": "Male",
    "Introduction": "tellus semper interdum mauris ullamcorper purus sit amet nulla quisque arcu libero rutrum ac lobortis vel dapibus",
    "KnownAs": "Cosme"
  },
  {
    "Username": "ycassam1",
    "Email": "yarlet1@weather.com",
    "Avatar": "https://robohash.org/uteafacilis.png?size=250x250&set=set1",
    "City": "Doibang",
    "DateOfBirth": "2021-06-18T11:32:20Z",
    "Gender": "Female",
    "Introduction": "ligula sit amet eleifend pede libero quis orci nullam molestie nibh in lectus pellentesque",
    "KnownAs": "Ynez"
  },
  {
    "Username": "etunnock2",
    "Email": "eashpole2@census.gov",
    "Avatar": "https://robohash.org/temporalaborumiure.png?size=250x250&set=set1",
    "City": "Jingguan",
    "DateOfBirth": "2017-08-21T00:32:57Z",
    "Gender": "Male",
    "Introduction": "eleifend donec ut dolor morbi vel lectus in quam fringilla rhoncus mauris enim leo rhoncus",
    "KnownAs": "Early"
  },
  {
    "Username": "cschuh3",
    "Email": "cjordanson3@state.tx.us",
    "Avatar": "https://robohash.org/eiuseumiste.png?size=250x250&set=set1",
    "City": "Vukovije Donje",
    "DateOfBirth": "2022-03-01T09:55:49Z",
    "Gender": "Female",
    "Introduction": "lectus pellentesque eget nunc donec quis orci eget orci vehicula condimentum curabitur in libero",
    "KnownAs": "Colly"
  },
  {
    "Username": "bdetloff4",
    "Email": "bpountain4@ning.com",
    "Avatar": "https://robohash.org/istedoloribusipsa.png?size=250x250&set=set1",
    "City": "Al Hāshimīyah",
    "DateOfBirth": "2019-05-03T06:55:00Z",
    "Gender": "Male",
    "Introduction": "proin eu mi nulla ac enim in tempor turpis nec euismod",
    "KnownAs": "Boycey"
  },
  {
    "Username": "amaken5",
    "Email": "alargan5@amazon.co.jp",
    "Avatar": "https://robohash.org/eteumea.png?size=250x250&set=set1",
    "City": "General Elizardo Aquino",
    "DateOfBirth": "2021-01-18T14:44:01Z",
    "Gender": "Female",
    "Introduction": "felis ut at dolor quis odio consequat varius integer ac leo pellentesque ultrices mattis odio donec vitae nisi",
    "KnownAs": "Anastasie"
  },
  {
    "Username": "rfonte6",
    "Email": "rhaliburton6@ifeng.com",
    "Avatar": "https://robohash.org/culpadoloresminima.png?size=250x250&set=set1",
    "City": "Xinchong",
    "DateOfBirth": "2020-09-22T14:20:07Z",
    "Gender": "Female",
    "Introduction": "hac habitasse platea dictumst morbi vestibulum velit id pretium iaculis diam erat fermentum justo nec condimentum neque sapien",
    "KnownAs": "Ramonda"
  },
  {
    "Username": "fbarme7",
    "Email": "ftompsett7@pen.io",
    "Avatar": "https://robohash.org/sitdistinctiodolorem.png?size=250x250&set=set1",
    "City": "Erdenet",
    "DateOfBirth": "2021-01-02T15:50:55Z",
    "Gender": "Female",
    "Introduction": "volutpat sapien arcu sed augue aliquam erat volutpat in congue etiam justo etiam pretium iaculis justo",
    "KnownAs": "Faythe"
  },
  {
    "Username": "bmargarson8",
    "Email": "bsaveall8@ameblo.jp",
    "Avatar": "https://robohash.org/minusassumendaat.png?size=250x250&set=set1",
    "City": "Kopstal",
    "DateOfBirth": "2020-11-27T10:29:21Z",
    "Gender": "Female",
    "Introduction": "in lacus curabitur at ipsum ac tellus semper interdum mauris ullamcorper purus sit",
    "KnownAs": "Beatriz"
  },
  {
    "Username": "mjellman9",
    "Email": "mtowne9@sakura.ne.jp",
    "Avatar": "https://robohash.org/voluptatesquasomnis.png?size=250x250&set=set1",
    "City": "Carmen",
    "DateOfBirth": "2022-08-02T12:14:04Z",
    "Gender": "Male",
    "Introduction": "convallis morbi odio odio elementum eu interdum eu tincidunt in leo maecenas pulvinar lobortis est phasellus sit amet",
    "KnownAs": "Mayne"
  },
  {
    "Username": "wchateleta",
    "Email": "wvandevliesa@amazon.co.uk",
    "Avatar": "https://robohash.org/itaquepraesentiumest.png?size=250x250&set=set1",
    "City": "Lesozavodsk",
    "DateOfBirth": "2019-08-26T08:12:06Z",
    "Gender": "Male",
    "Introduction": "tortor quis turpis sed ante vivamus tortor duis mattis egestas metus aenean fermentum donec",
    "KnownAs": "Wilfrid"
  },
  {
    "Username": "aoshielsb",
    "Email": "alaceb@soup.io",
    "Avatar": "https://robohash.org/solutaquonihil.png?size=250x250&set=set1",
    "City": "Ilagan",
    "DateOfBirth": "2020-03-28T00:33:17Z",
    "Gender": "Female",
    "Introduction": "aliquet at feugiat non pretium quis lectus suspendisse potenti in eleifend",
    "KnownAs": "Aubry"
  },
  {
    "Username": "dvalancec",
    "Email": "dwiltsherc@slideshare.net",
    "Avatar": "https://robohash.org/nequevitaemaxime.png?size=250x250&set=set1",
    "City": "Rancabugel",
    "DateOfBirth": "2021-11-07T09:30:45Z",
    "Gender": "Male",
    "Introduction": "curae duis faucibus accumsan odio curabitur convallis duis consequat dui nec nisi volutpat eleifend donec ut dolor morbi",
    "KnownAs": "Darn"
  },
  {
    "Username": "knussend",
    "Email": "ktwinamed@hubpages.com",
    "Avatar": "https://robohash.org/autemcumrerum.png?size=250x250&set=set1",
    "City": "Krueng Luak",
    "DateOfBirth": "2019-12-05T11:38:44Z",
    "Gender": "Female",
    "Introduction": "mi nulla ac enim in tempor turpis nec euismod scelerisque quam turpis adipiscing lorem vitae mattis nibh",
    "KnownAs": "Karia"
  },
  {
    "Username": "uloniee",
    "Email": "ucordeiroe@hp.com",
    "Avatar": "https://robohash.org/autillumaliquid.png?size=250x250&set=set1",
    "City": "Cantuk Kidul",
    "DateOfBirth": "2022-03-19T20:14:40Z",
    "Gender": "Male",
    "Introduction": "pulvinar nulla pede ullamcorper augue a suscipit nulla elit ac nulla sed vel enim",
    "KnownAs": "Ulberto"
  },
  {
    "Username": "sfurmedgef",
    "Email": "sgrenfellf@jalbum.net",
    "Avatar": "https://robohash.org/eosmolestiaequidem.png?size=250x250&set=set1",
    "City": "Vila Nova de Milfontes",
    "DateOfBirth": "2019-10-22T13:47:10Z",
    "Gender": "Female",
    "Introduction": "risus semper porta volutpat quam pede lobortis ligula sit amet eleifend pede libero quis orci nullam molestie nibh in",
    "KnownAs": "Shirline"
  },
  {
    "Username": "blynaghg",
    "Email": "bgabrielyg@wikispaces.com",
    "Avatar": "https://robohash.org/adnobisdeleniti.png?size=250x250&set=set1",
    "City": "Bell Ville",
    "DateOfBirth": "2019-08-19T22:55:10Z",
    "Gender": "Female",
    "Introduction": "in hac habitasse platea dictumst etiam faucibus cursus urna ut tellus nulla ut erat id",
    "KnownAs": "Brittney"
  },
  {
    "Username": "abenbowh",
    "Email": "ashovellerh@bing.com",
    "Avatar": "https://robohash.org/voluptatesutquam.png?size=250x250&set=set1",
    "City": "Pechenizhyn",
    "DateOfBirth": "2022-03-30T13:13:09Z",
    "Gender": "Female",
    "Introduction": "luctus rutrum nulla tellus in sagittis dui vel nisl duis ac nibh fusce lacus purus aliquet at",
    "KnownAs": "Annabal"
  },
  {
    "Username": "dferaghi",
    "Email": "dmousdalli@yelp.com",
    "Avatar": "https://robohash.org/rerumiustovoluptas.png?size=250x250&set=set1",
    "City": "Xiayang",
    "DateOfBirth": "2021-10-25T09:08:46Z",
    "Gender": "Female",
    "Introduction": "consectetuer eget rutrum at lorem integer tincidunt ante vel ipsum praesent blandit lacinia erat vestibulum sed magna at",
    "KnownAs": "Donny"
  },
  {
    "Username": "bbenardetj",
    "Email": "bmartlewj@naver.com",
    "Avatar": "https://robohash.org/etrerumnumquam.png?size=250x250&set=set1",
    "City": "Cikupa",
    "DateOfBirth": "2018-03-07T13:41:31Z",
    "Gender": "Male",
    "Introduction": "congue etiam justo etiam pretium iaculis justo in hac habitasse platea dictumst etiam faucibus cursus urna",
    "KnownAs": "Blayne"
  },
  {
    "Username": "sspadarok",
    "Email": "sdandok@xinhuanet.com",
    "Avatar": "https://robohash.org/eligendifacerenihil.png?size=250x250&set=set1",
    "City": "Deqing",
    "DateOfBirth": "2018-07-05T09:23:41Z",
    "Gender": "Male",
    "Introduction": "sapien in sapien iaculis congue vivamus metus arcu adipiscing molestie hendrerit at vulputate vitae",
    "KnownAs": "Salvatore"
  },
  {
    "Username": "dgreenroal",
    "Email": "dpawlickil@amazon.co.jp",
    "Avatar": "https://robohash.org/ametquibusdamqui.png?size=250x250&set=set1",
    "City": "Montbéliard",
    "DateOfBirth": "2019-07-03T16:01:46Z",
    "Gender": "Female",
    "Introduction": "orci luctus et ultrices posuere cubilia curae nulla dapibus dolor vel est donec odio justo sollicitudin ut suscipit a feugiat",
    "KnownAs": "Delilah"
  },
  {
    "Username": "bhelwigm",
    "Email": "bpietersm@mtv.com",
    "Avatar": "https://robohash.org/quimagnamdistinctio.png?size=250x250&set=set1",
    "City": "Omuthiya",
    "DateOfBirth": "2021-03-16T12:56:45Z",
    "Gender": "Male",
    "Introduction": "risus praesent lectus vestibulum quam sapien varius ut blandit non interdum in ante vestibulum ante ipsum primis in faucibus orci",
    "KnownAs": "Bevon"
  },
  {
    "Username": "snormanselln",
    "Email": "smcgannonn@economist.com",
    "Avatar": "https://robohash.org/laborumliberoqui.png?size=250x250&set=set1",
    "City": "Olsztyn",
    "DateOfBirth": "2022-08-03T09:47:09Z",
    "Gender": "Female",
    "Introduction": "in lacus curabitur at ipsum ac tellus semper interdum mauris ullamcorper purus sit amet nulla quisque",
    "KnownAs": "Shandee"
  },
  {
    "Username": "gglasspooleo",
    "Email": "gdarrigrando@joomla.org",
    "Avatar": "https://robohash.org/consecteturdoloremqueet.png?size=250x250&set=set1",
    "City": "Kamphaeng Phet",
    "DateOfBirth": "2018-02-11T05:12:45Z",
    "Gender": "Male",
    "Introduction": "ante ipsum primis in faucibus orci luctus et ultrices posuere cubilia curae",
    "KnownAs": "Giacopo"
  },
  {
    "Username": "usaycep",
    "Email": "uburnallp@columbia.edu",
    "Avatar": "https://robohash.org/blanditiisutquia.png?size=250x250&set=set1",
    "City": "Lubasz",
    "DateOfBirth": "2017-10-05T19:29:49Z",
    "Gender": "Male",
    "Introduction": "duis at velit eu est congue elementum in hac habitasse platea dictumst morbi vestibulum velit id pretium iaculis diam erat",
    "KnownAs": "Upton"
  },
  {
    "Username": "gdallewaterq",
    "Email": "grannieq@wikimedia.org",
    "Avatar": "https://robohash.org/ipsamodioasperiores.png?size=250x250&set=set1",
    "City": "Kertasari",
    "DateOfBirth": "2021-06-13T14:52:35Z",
    "Gender": "Male",
    "Introduction": "ac diam cras pellentesque volutpat dui maecenas tristique est et tempus semper est",
    "KnownAs": "Goddart"
  },
  {
    "Username": "hlosanor",
    "Email": "hburder@gnu.org",
    "Avatar": "https://robohash.org/inventorequidemvero.png?size=250x250&set=set1",
    "City": "Noveleta",
    "DateOfBirth": "2020-07-16T01:39:59Z",
    "Gender": "Male",
    "Introduction": "quisque porta volutpat erat quisque erat eros viverra eget congue eget semper rutrum nulla nunc purus phasellus in felis donec",
    "KnownAs": "Hilarius"
  },
  {
    "Username": "dodowgaines",
    "Email": "dalvaros@gnu.org",
    "Avatar": "https://robohash.org/recusandaecupiditateenim.png?size=250x250&set=set1",
    "City": "Neftçala",
    "DateOfBirth": "2017-05-19T02:26:33Z",
    "Gender": "Male",
    "Introduction": "tortor sollicitudin mi sit amet lobortis sapien sapien non mi integer ac neque duis bibendum morbi non quam nec",
    "KnownAs": "Domenic"
  },
  {
    "Username": "mbrinkwortht",
    "Email": "mdelasallet@oakley.com",
    "Avatar": "https://robohash.org/utvelitprovident.png?size=250x250&set=set1",
    "City": "Bedayu",
    "DateOfBirth": "2021-03-05T08:13:14Z",
    "Gender": "Female",
    "Introduction": "ut erat curabitur gravida nisi at nibh in hac habitasse platea dictumst aliquam augue quam sollicitudin vitae consectetuer eget rutrum",
    "KnownAs": "Milly"
  },
  {
    "Username": "ktomkinsonu",
    "Email": "kspiringu@kickstarter.com",
    "Avatar": "https://robohash.org/nonhicut.png?size=250x250&set=set1",
    "City": "Corona",
    "DateOfBirth": "2022-02-21T15:55:39Z",
    "Gender": "Male",
    "Introduction": "consequat dui nec nisi volutpat eleifend donec ut dolor morbi vel lectus in quam fringilla rhoncus mauris enim leo rhoncus",
    "KnownAs": "Kev"
  },
  {
    "Username": "mbraleyv",
    "Email": "mearlesv@tinypic.com",
    "Avatar": "https://robohash.org/dolorumdoloremamet.png?size=250x250&set=set1",
    "City": "Changgang",
    "DateOfBirth": "2022-08-10T06:52:49Z",
    "Gender": "Male",
    "Introduction": "lobortis convallis tortor risus dapibus augue vel accumsan tellus nisi eu orci mauris lacinia sapien quis libero nullam sit amet",
    "KnownAs": "Meredith"
  },
  {
    "Username": "tedgew",
    "Email": "tberggrenw@soundcloud.com",
    "Avatar": "https://robohash.org/nondolorillum.png?size=250x250&set=set1",
    "City": "Gorskaya",
    "DateOfBirth": "2021-05-24T14:32:25Z",
    "Gender": "Male",
    "Introduction": "platea dictumst aliquam augue quam sollicitudin vitae consectetuer eget rutrum",
    "KnownAs": "Thornton"
  },
  {
    "Username": "sdwirex",
    "Email": "scrimesx@4shared.com",
    "Avatar": "https://robohash.org/ipsumcumquerepudiandae.png?size=250x250&set=set1",
    "City": "Xiangfeng",
    "DateOfBirth": "2017-08-07T00:18:02Z",
    "Gender": "Male",
    "Introduction": "est lacinia nisi venenatis tristique fusce congue diam id ornare imperdiet sapien urna pretium nisl ut volutpat",
    "KnownAs": "Sandor"
  },
  {
    "Username": "mwoodally",
    "Email": "mdewitty@ycombinator.com",
    "Avatar": "https://robohash.org/dignissimosundeadipisci.png?size=250x250&set=set1",
    "City": "Al Wardānīn",
    "DateOfBirth": "2018-09-13T00:49:14Z",
    "Gender": "Male",
    "Introduction": "justo morbi ut odio cras mi pede malesuada in imperdiet et commodo vulputate justo in",
    "KnownAs": "Mason"
  },
  {
    "Username": "wpowellz",
    "Email": "wbamfordz@youtube.com",
    "Avatar": "https://robohash.org/voluptateaspernaturet.png?size=250x250&set=set1",
    "City": "Andrijaševci",
    "DateOfBirth": "2021-07-19T10:46:44Z",
    "Gender": "Female",
    "Introduction": "nulla elit ac nulla sed vel enim sit amet nunc viverra dapibus nulla",
    "KnownAs": "Willette"
  },
  {
    "Username": "lmatuszkiewicz10",
    "Email": "lhamberstone10@freewebs.com",
    "Avatar": "https://robohash.org/atcupiditatecum.png?size=250x250&set=set1",
    "City": "Pombal",
    "DateOfBirth": "2022-07-07T15:44:15Z",
    "Gender": "Female",
    "Introduction": "dictumst etiam faucibus cursus urna ut tellus nulla ut erat id mauris vulputate elementum",
    "KnownAs": "Lethia"
  },
  {
    "Username": "apocknell11",
    "Email": "aspinola11@umich.edu",
    "Avatar": "https://robohash.org/similiqueuttotam.png?size=250x250&set=set1",
    "City": "Bailieborough",
    "DateOfBirth": "2018-02-23T15:39:43Z",
    "Gender": "Female",
    "Introduction": "montes nascetur ridiculus mus vivamus vestibulum sagittis sapien cum sociis natoque penatibus et magnis dis parturient",
    "KnownAs": "Anthia"
  },
  {
    "Username": "spawels12",
    "Email": "sblackhall12@csmonitor.com",
    "Avatar": "https://robohash.org/vitaemaioreset.png?size=250x250&set=set1",
    "City": "Shalushka",
    "DateOfBirth": "2017-09-25T18:17:52Z",
    "Gender": "Male",
    "Introduction": "arcu libero rutrum ac lobortis vel dapibus at diam nam tristique tortor eu pede",
    "KnownAs": "Scarface"
  },
  {
    "Username": "jfinci13",
    "Email": "jkalderon13@cyberchimps.com",
    "Avatar": "https://robohash.org/ducimusrationeimpedit.png?size=250x250&set=set1",
    "City": "Zhangjiayuan",
    "DateOfBirth": "2022-01-05T22:28:49Z",
    "Gender": "Female",
    "Introduction": "varius ut blandit non interdum in ante vestibulum ante ipsum primis in faucibus orci luctus et",
    "KnownAs": "Jesselyn"
  },
  {
    "Username": "kwardall14",
    "Email": "kstetson14@e-recht24.de",
    "Avatar": "https://robohash.org/molestiaenonrepudiandae.png?size=250x250&set=set1",
    "City": "Safonovo",
    "DateOfBirth": "2022-01-27T19:25:07Z",
    "Gender": "Female",
    "Introduction": "curae duis faucibus accumsan odio curabitur convallis duis consequat dui nec nisi volutpat eleifend donec ut dolor morbi vel",
    "KnownAs": "Kameko"
  },
  {
    "Username": "bchieco15",
    "Email": "bgotthardsf15@biblegateway.com",
    "Avatar": "https://robohash.org/necessitatibussimiliquevelit.png?size=250x250&set=set1",
    "City": "Campos Belos",
    "DateOfBirth": "2018-10-21T20:39:24Z",
    "Gender": "Female",
    "Introduction": "odio curabitur convallis duis consequat dui nec nisi volutpat eleifend donec ut dolor",
    "KnownAs": "Barbey"
  },
  {
    "Username": "omcgeraghty16",
    "Email": "ohearst16@163.com",
    "Avatar": "https://robohash.org/quodetest.png?size=250x250&set=set1",
    "City": "Arkhaía Kórinthos",
    "DateOfBirth": "2019-03-06T17:13:32Z",
    "Gender": "Male",
    "Introduction": "elit ac nulla sed vel enim sit amet nunc viverra dapibus nulla suscipit ligula in lacus curabitur",
    "KnownAs": "Ogden"
  },
  {
    "Username": "mhodge17",
    "Email": "mgarlick17@alexa.com",
    "Avatar": "https://robohash.org/omnisdoloremofficiis.png?size=250x250&set=set1",
    "City": "Fudian",
    "DateOfBirth": "2019-08-03T09:34:00Z",
    "Gender": "Female",
    "Introduction": "nulla ultrices aliquet maecenas leo odio condimentum id luctus nec molestie sed justo pellentesque viverra pede ac",
    "KnownAs": "Manon"
  },
  {
    "Username": "ajorg18",
    "Email": "aglowach18@sciencedaily.com",
    "Avatar": "https://robohash.org/teneturenimplaceat.png?size=250x250&set=set1",
    "City": "Staraya Stanitsa",
    "DateOfBirth": "2021-06-14T12:27:08Z",
    "Gender": "Male",
    "Introduction": "eros elementum pellentesque quisque porta volutpat erat quisque erat eros viverra eget congue eget semper",
    "KnownAs": "Adolphe"
  },
  {
    "Username": "mgaven19",
    "Email": "mvarey19@slashdot.org",
    "Avatar": "https://robohash.org/involuptatesinventore.png?size=250x250&set=set1",
    "City": "Potok Złoty",
    "DateOfBirth": "2019-12-05T22:39:01Z",
    "Gender": "Female",
    "Introduction": "molestie nibh in lectus pellentesque at nulla suspendisse potenti cras in purus eu magna vulputate luctus cum sociis",
    "KnownAs": "Modesty"
  },
  {
    "Username": "mdewhirst1a",
    "Email": "mfoynes1a@cornell.edu",
    "Avatar": "https://robohash.org/impeditquiassumenda.png?size=250x250&set=set1",
    "City": "Beizhakou",
    "DateOfBirth": "2019-09-08T01:59:42Z",
    "Gender": "Male",
    "Introduction": "vivamus tortor duis mattis egestas metus aenean fermentum donec ut mauris eget massa",
    "KnownAs": "Martyn"
  },
  {
    "Username": "cweeden1b",
    "Email": "cmckiernan1b@mysql.com",
    "Avatar": "https://robohash.org/etquasiaut.png?size=250x250&set=set1",
    "City": "Pueblo",
    "DateOfBirth": "2018-07-15T12:01:58Z",
    "Gender": "Female",
    "Introduction": "pede libero quis orci nullam molestie nibh in lectus pellentesque at nulla suspendisse potenti cras",
    "KnownAs": "Cecily"
  },
  {
    "Username": "bmougel1c",
    "Email": "bmckeaney1c@taobao.com",
    "Avatar": "https://robohash.org/doloresvoluptatemnobis.png?size=250x250&set=set1",
    "City": "Evijärvi",
    "DateOfBirth": "2021-01-30T10:44:51Z",
    "Gender": "Male",
    "Introduction": "scelerisque quam turpis adipiscing lorem vitae mattis nibh ligula nec sem duis aliquam convallis nunc proin at",
    "KnownAs": "Benn"
  },
  {
    "Username": "dhaughin1d",
    "Email": "dyoodall1d@ovh.net",
    "Avatar": "https://robohash.org/voluptatumadipiscinam.png?size=250x250&set=set1",
    "City": "Lakeland",
    "DateOfBirth": "2017-09-18T16:19:13Z",
    "Gender": "Male",
    "Introduction": "justo pellentesque viverra pede ac diam cras pellentesque volutpat dui maecenas tristique est et tempus semper est",
    "KnownAs": "Dun"
  },
  {
    "Username": "dhackinge1e",
    "Email": "dcolls1e@marriott.com",
    "Avatar": "https://robohash.org/pariaturblanditiisaut.png?size=250x250&set=set1",
    "City": "Xiaoshan",
    "DateOfBirth": "2018-06-09T17:34:35Z",
    "Gender": "Male",
    "Introduction": "posuere cubilia curae duis faucibus accumsan odio curabitur convallis duis consequat dui nec nisi volutpat eleifend donec ut",
    "KnownAs": "Dun"
  },
  {
    "Username": "mmillam1f",
    "Email": "mganter1f@mapquest.com",
    "Avatar": "https://robohash.org/corporisetexpedita.png?size=250x250&set=set1",
    "City": "Petani",
    "DateOfBirth": "2022-04-01T03:12:55Z",
    "Gender": "Female",
    "Introduction": "metus vitae ipsum aliquam non mauris morbi non lectus aliquam",
    "KnownAs": "Marcelia"
  },
  {
    "Username": "kwaldie1g",
    "Email": "kchiverton1g@yahoo.com",
    "Avatar": "https://robohash.org/autestquis.png?size=250x250&set=set1",
    "City": "Pokrov",
    "DateOfBirth": "2019-09-30T05:04:24Z",
    "Gender": "Female",
    "Introduction": "congue etiam justo etiam pretium iaculis justo in hac habitasse platea dictumst etiam faucibus",
    "KnownAs": "Kippy"
  },
  {
    "Username": "amcgaffey1h",
    "Email": "aosmar1h@mapy.cz",
    "Avatar": "https://robohash.org/quieiuset.png?size=250x250&set=set1",
    "City": "Alangilanan",
    "DateOfBirth": "2019-02-01T20:32:38Z",
    "Gender": "Female",
    "Introduction": "duis ac nibh fusce lacus purus aliquet at feugiat non pretium quis lectus suspendisse potenti in eleifend quam a odio",
    "KnownAs": "Alysia"
  },
  {
    "Username": "mjehan1i",
    "Email": "mmctrustam1i@digg.com",
    "Avatar": "https://robohash.org/utdoloresincidunt.png?size=250x250&set=set1",
    "City": "Banjar Peguyangan",
    "DateOfBirth": "2017-05-18T10:36:56Z",
    "Gender": "Female",
    "Introduction": "sapien non mi integer ac neque duis bibendum morbi non quam nec dui luctus rutrum nulla tellus",
    "KnownAs": "Moria"
  },
  {
    "Username": "jtissier1j",
    "Email": "jcolclough1j@bing.com",
    "Avatar": "https://robohash.org/temporibussequianimi.png?size=250x250&set=set1",
    "City": "El Adelanto",
    "DateOfBirth": "2019-06-21T09:50:10Z",
    "Gender": "Female",
    "Introduction": "nulla tempus vivamus in felis eu sapien cursus vestibulum proin eu mi nulla ac",
    "KnownAs": "Judy"
  },
  {
    "Username": "tlowles1k",
    "Email": "tdiemer1k@canalblog.com",
    "Avatar": "https://robohash.org/etautet.png?size=250x250&set=set1",
    "City": "Igir-igir",
    "DateOfBirth": "2019-03-25T04:46:53Z",
    "Gender": "Female",
    "Introduction": "velit vivamus vel nulla eget eros elementum pellentesque quisque porta volutpat erat quisque erat eros viverra eget congue eget",
    "KnownAs": "Tess"
  },
  {
    "Username": "drominov1l",
    "Email": "dsparrow1l@washington.edu",
    "Avatar": "https://robohash.org/possimuslaborumquo.png?size=250x250&set=set1",
    "City": "Mishkino",
    "DateOfBirth": "2021-12-22T18:20:48Z",
    "Gender": "Male",
    "Introduction": "tortor risus dapibus augue vel accumsan tellus nisi eu orci mauris",
    "KnownAs": "Dewey"
  },
  {
    "Username": "cbalding1m",
    "Email": "cwhatsize1m@thetimes.co.uk",
    "Avatar": "https://robohash.org/temporedelenitirem.png?size=250x250&set=set1",
    "City": "Cicurug",
    "DateOfBirth": "2019-08-18T10:46:09Z",
    "Gender": "Male",
    "Introduction": "lacus curabitur at ipsum ac tellus semper interdum mauris ullamcorper purus sit amet nulla quisque arcu libero",
    "KnownAs": "Cart"
  },
  {
    "Username": "hizhakov1n",
    "Email": "hbeetles1n@latimes.com",
    "Avatar": "https://robohash.org/corruptinobisut.png?size=250x250&set=set1",
    "City": "Soanindrariny",
    "DateOfBirth": "2020-06-10T09:14:25Z",
    "Gender": "Female",
    "Introduction": "nisl aenean lectus pellentesque eget nunc donec quis orci eget orci vehicula condimentum curabitur in libero",
    "KnownAs": "Harrie"
  },
  {
    "Username": "hhillock1o",
    "Email": "hstilliard1o@hhs.gov",
    "Avatar": "https://robohash.org/laboriosamrepudiandaeconsequatur.png?size=250x250&set=set1",
    "City": "Tucupido",
    "DateOfBirth": "2021-01-22T19:06:24Z",
    "Gender": "Male",
    "Introduction": "nisi volutpat eleifend donec ut dolor morbi vel lectus in quam fringilla rhoncus mauris enim leo rhoncus",
    "KnownAs": "Horatio"
  },
  {
    "Username": "aspraggs1p",
    "Email": "acoaster1p@nbcnews.com",
    "Avatar": "https://robohash.org/sedminimadolore.png?size=250x250&set=set1",
    "City": "Lugang",
    "DateOfBirth": "2022-03-24T04:42:12Z",
    "Gender": "Female",
    "Introduction": "sed accumsan felis ut at dolor quis odio consequat varius integer ac leo pellentesque ultrices mattis odio donec",
    "KnownAs": "Arabelle"
  },
  {
    "Username": "tchavez1q",
    "Email": "tmatzkaitis1q@flickr.com",
    "Avatar": "https://robohash.org/abvoluptatemnostrum.png?size=250x250&set=set1",
    "City": "Huachos",
    "DateOfBirth": "2021-02-10T21:14:55Z",
    "Gender": "Female",
    "Introduction": "vel nulla eget eros elementum pellentesque quisque porta volutpat erat quisque erat eros viverra eget congue eget semper rutrum nulla",
    "KnownAs": "Tarrah"
  },
  {
    "Username": "rfilipic1r",
    "Email": "rcallingham1r@chron.com",
    "Avatar": "https://robohash.org/autemdelectusaut.png?size=250x250&set=set1",
    "City": "Adamstown",
    "DateOfBirth": "2022-05-18T12:51:19Z",
    "Gender": "Female",
    "Introduction": "sapien dignissim vestibulum vestibulum ante ipsum primis in faucibus orci luctus et ultrices posuere",
    "KnownAs": "Renata"
  },
  {
    "Username": "tmendus1s",
    "Email": "tmanagh1s@springer.com",
    "Avatar": "https://robohash.org/architectoexcepturiqui.png?size=250x250&set=set1",
    "City": "Tabalong",
    "DateOfBirth": "2019-02-05T16:01:53Z",
    "Gender": "Female",
    "Introduction": "sapien urna pretium nisl ut volutpat sapien arcu sed augue aliquam erat volutpat in congue etiam justo etiam",
    "KnownAs": "Trista"
  },
  {
    "Username": "cdonaher1t",
    "Email": "ccrowthe1t@cam.ac.uk",
    "Avatar": "https://robohash.org/autlaboriosameos.png?size=250x250&set=set1",
    "City": "Kaduheuleut",
    "DateOfBirth": "2019-02-28T10:55:12Z",
    "Gender": "Male",
    "Introduction": "suscipit ligula in lacus curabitur at ipsum ac tellus semper interdum mauris ullamcorper purus sit amet nulla quisque arcu",
    "KnownAs": "Claiborn"
  },
  {
    "Username": "jgillott1u",
    "Email": "jberick1u@whitehouse.gov",
    "Avatar": "https://robohash.org/similiqueestodio.png?size=250x250&set=set1",
    "City": "Orlando",
    "DateOfBirth": "2017-06-21T06:00:12Z",
    "Gender": "Female",
    "Introduction": "donec pharetra magna vestibulum aliquet ultrices erat tortor sollicitudin mi sit amet lobortis sapien sapien non mi integer ac neque",
    "KnownAs": "Jenica"
  },
  {
    "Username": "ebrahmer1v",
    "Email": "egreeveson1v@cbsnews.com",
    "Avatar": "https://robohash.org/eaqueofficiaaccusamus.png?size=250x250&set=set1",
    "City": "Fernando Gutierrez Barrios",
    "DateOfBirth": "2018-03-18T09:57:54Z",
    "Gender": "Male",
    "Introduction": "blandit nam nulla integer pede justo lacinia eget tincidunt eget tempus vel pede morbi porttitor lorem id ligula suspendisse ornare",
    "KnownAs": "Erastus"
  },
  {
    "Username": "hgarfath1w",
    "Email": "hrheaume1w@macromedia.com",
    "Avatar": "https://robohash.org/eumquinulla.png?size=250x250&set=set1",
    "City": "Fujia",
    "DateOfBirth": "2017-11-27T13:36:52Z",
    "Gender": "Male",
    "Introduction": "purus phasellus in felis donec semper sapien a libero nam dui proin leo odio",
    "KnownAs": "Hamilton"
  },
  {
    "Username": "klansdale1x",
    "Email": "kspence1x@omniture.com",
    "Avatar": "https://robohash.org/perferendisquototam.png?size=250x250&set=set1",
    "City": "Kurunegala",
    "DateOfBirth": "2018-08-22T02:32:57Z",
    "Gender": "Female",
    "Introduction": "enim blandit mi in porttitor pede justo eu massa donec",
    "KnownAs": "Kris"
  },
  {
    "Username": "oevershed1y",
    "Email": "ogaskamp1y@nbcnews.com",
    "Avatar": "https://robohash.org/namlaudantiumsunt.png?size=250x250&set=set1",
    "City": "Sanjian",
    "DateOfBirth": "2021-01-21T19:48:13Z",
    "Gender": "Female",
    "Introduction": "morbi porttitor lorem id ligula suspendisse ornare consequat lectus in est risus auctor",
    "KnownAs": "Odelinda"
  },
  {
    "Username": "dandrzej1z",
    "Email": "dsnoden1z@hostgator.com",
    "Avatar": "https://robohash.org/esteaexplicabo.png?size=250x250&set=set1",
    "City": "Vysotsk",
    "DateOfBirth": "2018-10-19T23:32:20Z",
    "Gender": "Male",
    "Introduction": "vulputate ut ultrices vel augue vestibulum ante ipsum primis in faucibus orci luctus et ultrices posuere cubilia curae",
    "KnownAs": "Darnall"
  },
  {
    "Username": "dpactat20",
    "Email": "dtarling20@sun.com",
    "Avatar": "https://robohash.org/itaqueharumbeatae.png?size=250x250&set=set1",
    "City": "Yandang",
    "DateOfBirth": "2020-06-16T16:19:47Z",
    "Gender": "Male",
    "Introduction": "venenatis turpis enim blandit mi in porttitor pede justo eu massa donec",
    "KnownAs": "Derward"
  },
  {
    "Username": "ggodspeede21",
    "Email": "gtyzack21@plala.or.jp",
    "Avatar": "https://robohash.org/porroenimlaborum.png?size=250x250&set=set1",
    "City": "Nyimba",
    "DateOfBirth": "2017-08-29T09:19:30Z",
    "Gender": "Female",
    "Introduction": "felis eu sapien cursus vestibulum proin eu mi nulla ac enim in tempor turpis nec euismod scelerisque quam",
    "KnownAs": "Grata"
  },
  {
    "Username": "drackam22",
    "Email": "dmarkey22@ed.gov",
    "Avatar": "https://robohash.org/quianullaut.png?size=250x250&set=set1",
    "City": "Naukšēni",
    "DateOfBirth": "2021-07-06T06:13:46Z",
    "Gender": "Male",
    "Introduction": "sapien in sapien iaculis congue vivamus metus arcu adipiscing molestie hendrerit at vulputate vitae",
    "KnownAs": "Dimitri"
  },
  {
    "Username": "zbudnik23",
    "Email": "zmchirrie23@angelfire.com",
    "Avatar": "https://robohash.org/totamexcepturiaccusantium.png?size=250x250&set=set1",
    "City": "Cibitung",
    "DateOfBirth": "2017-09-11T09:52:42Z",
    "Gender": "Female",
    "Introduction": "congue etiam justo etiam pretium iaculis justo in hac habitasse platea dictumst etiam faucibus cursus urna ut tellus",
    "KnownAs": "Zorine"
  },
  {
    "Username": "fmordon24",
    "Email": "fheinritz24@a8.net",
    "Avatar": "https://robohash.org/errorvoluptasnobis.png?size=250x250&set=set1",
    "City": "Altares",
    "DateOfBirth": "2020-05-08T14:21:44Z",
    "Gender": "Male",
    "Introduction": "fermentum justo nec condimentum neque sapien placerat ante nulla justo aliquam quis turpis eget elit sodales scelerisque mauris sit",
    "KnownAs": "Farris"
  },
  {
    "Username": "gburds25",
    "Email": "gbryde25@freewebs.com",
    "Avatar": "https://robohash.org/quaebeataeet.png?size=250x250&set=set1",
    "City": "Ringinagung",
    "DateOfBirth": "2018-03-12T17:54:16Z",
    "Gender": "Female",
    "Introduction": "ultrices erat tortor sollicitudin mi sit amet lobortis sapien sapien non mi integer ac neque",
    "KnownAs": "Gwendolyn"
  },
  {
    "Username": "faxcel26",
    "Email": "fcowlin26@facebook.com",
    "Avatar": "https://robohash.org/delenitiautlaboriosam.png?size=250x250&set=set1",
    "City": "Xilaiqiao",
    "DateOfBirth": "2019-03-13T01:49:42Z",
    "Gender": "Male",
    "Introduction": "fermentum donec ut mauris eget massa tempor convallis nulla neque",
    "KnownAs": "Flint"
  },
  {
    "Username": "beriksson27",
    "Email": "bhowle27@sohu.com",
    "Avatar": "https://robohash.org/blanditiisutfacilis.png?size=250x250&set=set1",
    "City": "Pobral",
    "DateOfBirth": "2022-10-19T15:04:33Z",
    "Gender": "Female",
    "Introduction": "amet lobortis sapien sapien non mi integer ac neque duis bibendum morbi",
    "KnownAs": "Babette"
  },
  {
    "Username": "jcockerham28",
    "Email": "jskett28@live.com",
    "Avatar": "https://robohash.org/veroquisvelit.png?size=250x250&set=set1",
    "City": "Atibaia",
    "DateOfBirth": "2017-09-19T11:34:08Z",
    "Gender": "Female",
    "Introduction": "vivamus vel nulla eget eros elementum pellentesque quisque porta volutpat erat quisque erat eros viverra eget congue eget semper rutrum",
    "KnownAs": "Jeannette"
  },
  {
    "Username": "tlille29",
    "Email": "thorwell29@foxnews.com",
    "Avatar": "https://robohash.org/consequunturvoluptatemenim.png?size=250x250&set=set1",
    "City": "La Rochelle",
    "DateOfBirth": "2018-10-09T20:30:19Z",
    "Gender": "Male",
    "Introduction": "ligula vehicula consequat morbi a ipsum integer a nibh in quis",
    "KnownAs": "Tedmund"
  },
  {
    "Username": "hswalwel2a",
    "Email": "hsmallcomb2a@prnewswire.com",
    "Avatar": "https://robohash.org/eaquisvoluptatem.png?size=250x250&set=set1",
    "City": "Milaor",
    "DateOfBirth": "2018-09-15T01:44:29Z",
    "Gender": "Male",
    "Introduction": "ante vivamus tortor duis mattis egestas metus aenean fermentum donec",
    "KnownAs": "Herold"
  },
  {
    "Username": "wthornley2b",
    "Email": "wrozsa2b@typepad.com",
    "Avatar": "https://robohash.org/etnatussint.png?size=250x250&set=set1",
    "City": "Suvorovskaya",
    "DateOfBirth": "2020-12-12T20:01:11Z",
    "Gender": "Male",
    "Introduction": "duis faucibus accumsan odio curabitur convallis duis consequat dui nec nisi volutpat eleifend",
    "KnownAs": "Wilek"
  },
  {
    "Username": "bculp2c",
    "Email": "blandall2c@diigo.com",
    "Avatar": "https://robohash.org/atquisquamanimi.png?size=250x250&set=set1",
    "City": "Shicha",
    "DateOfBirth": "2019-04-17T14:07:29Z",
    "Gender": "Male",
    "Introduction": "ultrices mattis odio donec vitae nisi nam ultrices libero non mattis pulvinar",
    "KnownAs": "Broderic"
  },
  {
    "Username": "tvaud2d",
    "Email": "tvotier2d@studiopress.com",
    "Avatar": "https://robohash.org/teneturnamaliquam.png?size=250x250&set=set1",
    "City": "Basco",
    "DateOfBirth": "2019-08-23T17:22:51Z",
    "Gender": "Male",
    "Introduction": "condimentum id luctus nec molestie sed justo pellentesque viverra pede ac diam cras pellentesque",
    "KnownAs": "Talbot"
  },
  {
    "Username": "cmatieu2e",
    "Email": "chume2e@fema.gov",
    "Avatar": "https://robohash.org/etlaboreanimi.png?size=250x250&set=set1",
    "City": "Saint Louis",
    "DateOfBirth": "2019-02-12T13:18:42Z",
    "Gender": "Female",
    "Introduction": "sit amet consectetuer adipiscing elit proin interdum mauris non ligula pellentesque ultrices phasellus id sapien in sapien iaculis",
    "KnownAs": "Cariotta"
  },
  {
    "Username": "kmchan2f",
    "Email": "kpatriskson2f@tuttocitta.it",
    "Avatar": "https://robohash.org/etnisiquaerat.png?size=250x250&set=set1",
    "City": "Perené",
    "DateOfBirth": "2021-05-14T08:05:43Z",
    "Gender": "Male",
    "Introduction": "nullam porttitor lacus at turpis donec posuere metus vitae ipsum aliquam non mauris morbi",
    "KnownAs": "Konrad"
  },
  {
    "Username": "hwelford2g",
    "Email": "hscates2g@sitemeter.com",
    "Avatar": "https://robohash.org/veritatisnostrumdolorem.png?size=250x250&set=set1",
    "City": "Jalatrang",
    "DateOfBirth": "2018-04-03T04:48:15Z",
    "Gender": "Male",
    "Introduction": "faucibus cursus urna ut tellus nulla ut erat id mauris vulputate elementum nullam varius nulla facilisi cras non velit nec",
    "KnownAs": "Hunter"
  },
  {
    "Username": "ldalgardno2h",
    "Email": "lmyrtle2h@time.com",
    "Avatar": "https://robohash.org/magnamconsequaturtempora.png?size=250x250&set=set1",
    "City": "Vasil’yevskiy Mokh",
    "DateOfBirth": "2019-09-11T10:49:52Z",
    "Gender": "Female",
    "Introduction": "turpis adipiscing lorem vitae mattis nibh ligula nec sem duis aliquam convallis nunc proin at turpis a pede posuere nonummy",
    "KnownAs": "Leena"
  },
  {
    "Username": "whaldin2i",
    "Email": "wzellmer2i@deliciousdays.com",
    "Avatar": "https://robohash.org/voluptatedoloresdolores.png?size=250x250&set=set1",
    "City": "Ccuntuma",
    "DateOfBirth": "2022-06-16T23:41:29Z",
    "Gender": "Male",
    "Introduction": "lectus in quam fringilla rhoncus mauris enim leo rhoncus sed vestibulum sit amet cursus id turpis integer aliquet massa",
    "KnownAs": "Waylin"
  },
  {
    "Username": "shardaway2j",
    "Email": "sdoudney2j@arstechnica.com",
    "Avatar": "https://robohash.org/impeditautnisi.png?size=250x250&set=set1",
    "City": "Cikadongdong",
    "DateOfBirth": "2020-09-04T08:35:06Z",
    "Gender": "Female",
    "Introduction": "nulla dapibus dolor vel est donec odio justo sollicitudin ut suscipit a feugiat",
    "KnownAs": "Shanna"
  },
  {
    "Username": "jpaule2k",
    "Email": "jkagan2k@berkeley.edu",
    "Avatar": "https://robohash.org/consequaturfacilisanimi.png?size=250x250&set=set1",
    "City": "Ndano",
    "DateOfBirth": "2017-07-31T05:30:28Z",
    "Gender": "Female",
    "Introduction": "felis ut at dolor quis odio consequat varius integer ac leo pellentesque ultrices mattis odio donec",
    "KnownAs": "Jolee"
  },
  {
    "Username": "ldincke2l",
    "Email": "ltipple2l@constantcontact.com",
    "Avatar": "https://robohash.org/dolorauteum.png?size=250x250&set=set1",
    "City": "Myingyan",
    "DateOfBirth": "2019-02-10T08:55:32Z",
    "Gender": "Female",
    "Introduction": "proin interdum mauris non ligula pellentesque ultrices phasellus id sapien in sapien iaculis congue",
    "KnownAs": "Lizbeth"
  },
  {
    "Username": "scassam2m",
    "Email": "shinemoor2m@zimbio.com",
    "Avatar": "https://robohash.org/utquosiure.png?size=250x250&set=set1",
    "City": "Tríkeri",
    "DateOfBirth": "2021-08-04T21:30:12Z",
    "Gender": "Male",
    "Introduction": "congue vivamus metus arcu adipiscing molestie hendrerit at vulputate vitae nisl aenean lectus",
    "KnownAs": "Skyler"
  },
  {
    "Username": "csamarth2n",
    "Email": "cclapton2n@yelp.com",
    "Avatar": "https://robohash.org/magnamomniseum.png?size=250x250&set=set1",
    "City": "Kaltungo",
    "DateOfBirth": "2020-03-20T08:03:55Z",
    "Gender": "Female",
    "Introduction": "orci vehicula condimentum curabitur in libero ut massa volutpat convallis",
    "KnownAs": "Celka"
  },
  {
    "Username": "akenner2o",
    "Email": "aoulet2o@bbb.org",
    "Avatar": "https://robohash.org/hicrerumeos.png?size=250x250&set=set1",
    "City": "Xinhua",
    "DateOfBirth": "2017-08-08T01:14:54Z",
    "Gender": "Female",
    "Introduction": "eget eros elementum pellentesque quisque porta volutpat erat quisque erat eros",
    "KnownAs": "Arliene"
  },
  {
    "Username": "wfancott2p",
    "Email": "wsplevings2p@reference.com",
    "Avatar": "https://robohash.org/solutaaaccusantium.png?size=250x250&set=set1",
    "City": "Pital",
    "DateOfBirth": "2020-02-05T14:14:43Z",
    "Gender": "Male",
    "Introduction": "fringilla rhoncus mauris enim leo rhoncus sed vestibulum sit amet cursus id turpis integer aliquet massa id lobortis convallis",
    "KnownAs": "William"
  },
  {
    "Username": "cluckcock2q",
    "Email": "cvassano2q@hc360.com",
    "Avatar": "https://robohash.org/inventorevelitfacilis.png?size=250x250&set=set1",
    "City": "Zaliznychne",
    "DateOfBirth": "2021-03-31T01:09:53Z",
    "Gender": "Female",
    "Introduction": "in hac habitasse platea dictumst morbi vestibulum velit id pretium iaculis diam",
    "KnownAs": "Christin"
  },
  {
    "Username": "ghonnan2r",
    "Email": "gechalier2r@xrea.com",
    "Avatar": "https://robohash.org/nullacommodiaut.png?size=250x250&set=set1",
    "City": "Mataguži",
    "DateOfBirth": "2018-07-11T04:40:58Z",
    "Gender": "Male",
    "Introduction": "in tempor turpis nec euismod scelerisque quam turpis adipiscing lorem vitae mattis nibh ligula nec sem duis aliquam convallis nunc",
    "KnownAs": "Gage"
  }
]